lmn/cx/y22/operating_systems/__init__.py
lmn/cx/y22/operating_systems/_operating_systems.py
lmn.cx.y22.operating_systems-3.0.dist-info/0BSD.txt
lmn.cx.y22.operating_systems-3.0.dist-info/Apache-2.0.txt
lmn.cx.y22.operating_systems-3.0.dist-info/CC0-1.0.txt
lmn.cx.y22.operating_systems-3.0.dist-info/COPYING
lmn.cx.y22.operating_systems-3.0.dist-info/METADATA
lmn.cx.y22.operating_systems-3.0.dist-info/MIT.txt
lmn.cx.y22.operating_systems-3.0.dist-info/WHEEL
lmn.cx.y22.operating_systems-3.0.dist-info/top_level.txt
lmn.cx.y22.operating_systems-3.0.dist-info/RECORD
